{
  "metadata": {
    "basic_info": {
      "filename": "20250921_002109_images_3.jfif",
      "file_size": 6972,
      "dimensions": "182x276",
      "width": 182,
      "height": 276,
      "format": "JPEG",
      "mode": "RGB",
      "has_transparency": false
    },
    "exif_data": {},
    "gps_data": {},
    "ocr_text": "No text detected",
    "analysis_timestamp": "2025-09-21T00:21:09.205686"
  },
  "reverse_search": {
    "matches_found": 0,
    "total_indexed": 0,
    "search_engines": [
      "AI Validation"
    ],
    "results": [],
    "search_message": "No matches found in global databases - image appears to be unique",
    "similarity_analysis": {
      "dimensions": "182x276",
      "file_size_kb": 6,
      "feature_points": 587,
      "brightness_level": 60.57170727822902,
      "contrast_level": 63.54002111373536,
      "color_channels": 3,
      "uniqueness_score": 0.74,
      "complexity_level": "high"
    },
    "authenticity_indicators": {
      "overall_authenticity": "highly_authentic",
      "manipulation_probability": "very_low",
      "quality_assessment": "excellent",
      "metadata_consistency": "consistent",
      "technical_analysis": [
        "\u2713 High feature density suggests natural photography",
        "\u2713 Natural brightness distribution",
        "\u2713 Healthy contrast levels indicate natural imaging",
        "\u26a0 Heavily compressed - possible quality degradation",
        "\u25d0 Non-standard aspect ratio - possible cropping or editing",
        "\u25d0 Moderate uniqueness characteristics",
        "\u2713 Technical metadata appears consistent"
      ],
      "technical_scores": {
        "feature_density": 11685.8,
        "brightness_score": 60.57170727822902,
        "contrast_score": 63.54002111373536,
        "compression_ratio": 0.041,
        "uniqueness_score": 0.74,
        "manipulation_score": 0.15
      }
    },
    "ai_detection": {
      "ai_probability": 0.25,
      "ai_probability_percentage": 25.0,
      "assessment": "likely_authentic",
      "confidence": "High",
      "risk_level": "SAFE",
      "indicators": [
        "\u2022 PicIntel Local Analysis: 20.0% AI probability",
        "\u2022 Hugging Face AI Detector: 30.0% AI probability"
      ],
      "individual_results": [
        {
          "service": "PicIntel Local Analysis",
          "ai_probability": 20.0,
          "assessment": "likely_authentic",
          "confidence": "High"
        },
        {
          "service": "Hugging Face AI Detector",
          "ai_probability": 30.0,
          "confidence": "Low",
          "assessment": "model_loading",
          "note": "Model is loading, try again in a moment"
        }
      ],
      "analysis_method": "Multi-API Consensus Analysis",
      "models_checked": [
        "PicIntel Local Analysis",
        "Hugging Face AI Detector"
      ],
      "timestamp": "2025-09-21T00:21:13.609147"
    },
    "search_timestamp": "2025-09-21T00:21:13.610147",
    "search_duration": "2.6 seconds"
  },
  "filename": "20250921_002109_images_3.jfif",
  "analysis_complete": true,
  "upload_time": "2025-09-21T00:21:13.610213"
}